setup.py
django_ballads/__init__.py
django_ballads/ballad.py
django_ballads/exceptions.py
django_ballads/models.py
django_ballads/tests.py
django_ballads.egg-info/PKG-INFO
django_ballads.egg-info/SOURCES.txt
django_ballads.egg-info/dependency_links.txt
django_ballads.egg-info/requires.txt
django_ballads.egg-info/top_level.txt