Metadata-Version: 1.0
Name: django-ballads
Version: 0.2
Summary: Django library for coordinating multi-system transactions (eg database, filesystem, remote API calls).
Home-page: https://github.com/jaylett/django-ballads
Author: James Aylett
Author-email: james@tartarus.org
License: MIT
Platform: UNKNOWN
Classifier: Intended Audience :: Developers
Classifier: Framework :: Django
Classifier: License :: OSI Approved :: MIT License
Classifier: Programming Language :: Python :: 2
